pyuniprot/CC.py
pyuniprot/DB.py
pyuniprot/UniRef.py
pyuniprot/Uniprot.py
pyuniprot/__init__.py
pyuniprot/py.typed
pyuniprot/version.py
pyuniprot/utils/__init__.py
pyuniprot/utils/isoforms.py
tests/__init__.py
tests/conftest.py
tests/test_isoforms.py
tests/test_uniprot.py
tests/test_uniref.py
pyuniprotkb-0.4.1.dist-info/LICENSE
pyuniprotkb-0.4.1.dist-info/METADATA
pyuniprotkb-0.4.1.dist-info/WHEEL
pyuniprotkb-0.4.1.dist-info/top_level.txt
pyuniprotkb-0.4.1.dist-info/RECORD
