Metadata-Version: 2.1
Name: pyuniprotkb
Version: 0.4.1
Summary: A python package to retrieve bioinformatics given Uniprot IDs.
Home-page: https://github.com/Ruibin-Liu/pyuniprot
Author: Ruibin Liu
Author-email: ruibinliuphd@gmail.com
Project-URL: Bug Tracker, https://github.com/Ruibin-Liu/pyuniprot/issues
Classifier: Programming Language :: Python :: 3
Classifier: License :: OSI Approved :: MIT License
Classifier: Operating System :: OS Independent
Requires-Python: >=3.7
License-File: LICENSE
Provides-Extra: testing
Requires-Dist: tox >=3.24 ; extra == 'testing'
Requires-Dist: pytest >=7.0 ; extra == 'testing'
Requires-Dist: pytest-cov >=3.0 ; extra == 'testing'
